ipaddr_range/__init__.py
ipaddr_range/iprange.py
ipaddr_range-0.0.1.dist-info/METADATA
ipaddr_range-0.0.1.dist-info/WHEEL
ipaddr_range-0.0.1.dist-info/RECORD
