Metadata-Version: 2.1
Name: ipaddr-range
Version: 0.0.1
Summary: Generating a list of IP addresses of IPv4 and IPv6 versions.
License: MIT
Author: Ivan Migunov
Author-email: im@fckg.ru
Requires-Python: >=3.11,<4.0
Classifier: License :: OSI Approved :: MIT License
Classifier: Programming Language :: Python :: 3
Classifier: Programming Language :: Python :: 3.11
